{
    "2308.10848": {
        "paper_id": "2308.10848",
        "abs_url": "https://arxiv.org/abs/2308.10848",
        "pdf_url": "https://arxiv.org/pdf/2308.10848.pdf",
        "supp_url": null,
        "src_website": "ArXiv",
        "download_name": "2308.10848_AgentVerse_Facilitating_Multi-Agent_Collaboration_and_Exploring_Emergent_Behaviors.pdf",
        "title": "AgentVerse: Facilitating Multi-Agent Collaboration and Exploring Emergent Behaviors",
        "year": null,
        "paper_venue": null,
        "authors": [
            "Weize Chen",
            "Yusheng Su",
            "Jingwei Zuo",
            "Cheng Yang",
            "Chenfei Yuan",
            "Chi-Min Chan",
            "Heyang Yu",
            "Yaxi Lu",
            "Yi-Hsin Hung",
            "Chen Qian",
            "Yujia Qin",
            "Xin Cong",
            "Ruobing Xie",
            "Zhiyuan Liu",
            "Maosong Sun",
            "Jie Zhou"
        ],
        "abstract": "}.",
        "comments": "Under review. Code at this https URL",
        "official_code_urls": [
            "https://github.com/openbmb/agentverse"
        ],
        "pwc_page_url": "https://paperswithcode.com/paper/agentverse-facilitating-multi-agent",
        "bibtex": "@misc{chen2023agentverse,\n      title={AgentVerse: Facilitating Multi-Agent Collaboration and Exploring Emergent Behaviors}, \n      author={Weize Chen and Yusheng Su and Jingwei Zuo and Cheng Yang and Chenfei Yuan and Chi-Min Chan and Heyang Yu and Yaxi Lu and Yi-Hsin Hung and Chen Qian and Yujia Qin and Xin Cong and Ruobing Xie and Zhiyuan Liu and Maosong Sun and Jie Zhou},\n      year={2023},\n      eprint={2308.10848},\n      archivePrefix={arXiv},\n      primaryClass={cs.CL}\n}"
    }
}