{
    "2212.10560": {
        "paper_id": "2212.10560",
        "abs_url": "https://arxiv.org/abs/2212.10560",
        "pdf_url": "https://arxiv.org/pdf/2212.10560.pdf",
        "supp_url": null,
        "src_website": "ArXiv",
        "download_name": "2212.10560_Self-Instruct_Aligning_Language_Models_with_Self-Generated_Instructions.pdf",
        "title": "Self-Instruct: Aligning Language Models with Self-Generated Instructions",
        "year": null,
        "paper_venue": null,
        "authors": [
            "Yizhong Wang",
            "Yeganeh Kordi",
            "Swaroop Mishra",
            "Alisa Liu",
            "Noah A. Smith",
            "Daniel Khashabi",
            "Hannaneh Hajishirzi"
        ],
        "abstract": ".",
        "comments": "ACL 2023 camera ready, 23 pages, 9 figures, 11 tables",
        "official_code_urls": [
            "https://github.com/yizhongw/self-instruct",
            "https://github.com/tatsu-lab/stanford_alpaca"
        ],
        "pwc_page_url": "https://paperswithcode.com/paper/self-instruct-aligning-language-model-with",
        "bibtex": "@misc{wang2023selfinstruct,\n      title={Self-Instruct: Aligning Language Models with Self-Generated Instructions}, \n      author={Yizhong Wang and Yeganeh Kordi and Swaroop Mishra and Alisa Liu and Noah A. Smith and Daniel Khashabi and Hannaneh Hajishirzi},\n      year={2023},\n      eprint={2212.10560},\n      archivePrefix={arXiv},\n      primaryClass={cs.CL}\n}"
    }
}